rocketunits/__init__.py
rocketunits/py_math_parser.py
rocketunits/rocket_units.py
rocketunits/tk_rocket_units.py
rocketunits/units_io.py
rocketunits/examples/displacement.py
rocketunits/examples/distance.py
rocketunits/examples/dv_rocket.py
rocketunits/examples/dv_rocket_v2.py
rocketunits/examples/example_1.py
rocketunits/examples/example_2.py
rocketunits/examples/example_3.py
rocketunits/tests/__init__.py
rocketunits/tests/test_pint_values.py
rocketunits/tests/test_rocket_units.py
rocketunits/tests/test_units_io.py
rocketunits-0.1.11.dist-info/AUTHORS.rst
rocketunits-0.1.11.dist-info/LICENSE
rocketunits-0.1.11.dist-info/LICENSE.txt
rocketunits-0.1.11.dist-info/METADATA
rocketunits-0.1.11.dist-info/WHEEL
rocketunits-0.1.11.dist-info/entry_points.txt
rocketunits-0.1.11.dist-info/top_level.txt
rocketunits-0.1.11.dist-info/RECORD
