Metadata-Version: 2.1
Name: rocketunits
Version: 0.1.11
Summary: RocketUnits provides a graphic user interface (GUI) for engineering units conversion.
Home-page: http://rocketunits.readthedocs.org/en/latest/
Author: Charlie Taylor
Author-email: cet@appliedpython.com
License: GPL-3
Download-URL: https://github.com/sonofeft/RocketUnits
Provides-Extra: dev
Requires-Dist: check-manifest ; extra == 'dev'
Provides-Extra: test
Requires-Dist: coverage ; extra == 'test'
